nisnap/__init__.py
nisnap/snap.py
nisnap/xnat.py
nisnap/utils/__init__.py
nisnap/utils/aseg.py
nisnap/utils/colormap.json
nisnap/utils/montage.py
nisnap/utils/parse.py
nisnap/utils/slices.py
nisnap-0.4.1.data/scripts/nisnap
nisnap-0.4.1.dist-info/LICENSE
nisnap-0.4.1.dist-info/METADATA
nisnap-0.4.1.dist-info/WHEEL
nisnap-0.4.1.dist-info/top_level.txt
nisnap-0.4.1.dist-info/RECORD
