Metadata-Version: 2.1
Name: nisnap
Version: 0.4.1
Summary: nisnap
Home-page: https://github.com/xgrg/nisnap
Author: Greg Operto
Author-email: goperto@barcelonabeta.org
License: UNKNOWN
Download-URL: https://github.com/xgrg/nisnap/-/archive/v0.4.1/nisnap-v0.4.1.tar.gz
Platform: UNKNOWN
Classifier: Intended Audience :: Science/Research
Classifier: Intended Audience :: Developers
Classifier: Topic :: Scientific/Engineering
Classifier: Operating System :: Unix
Classifier: Programming Language :: Python :: 3.8
Requires-Dist: Pillow (>=7.0)
Requires-Dist: coverage (>=4.5)
Requires-Dist: ipython (>=7.3)
Requires-Dist: matplotlib (>=3.1)
Requires-Dist: nibabel (>=2.0)
Requires-Dist: nilearn (>=0.8)
Requires-Dist: nose (>=1.3)
Requires-Dist: numpy (>=1.16)
Requires-Dist: pyxnat (>=1.3)
Requires-Dist: tqdm (>=4.31)
Requires-Dist: urllib3 (>=1.24)
